bhvideoconverter/__init__.py
bhvideoconverter/main.py
bhvideoconverter/controllers/__init__.py
bhvideoconverter/controllers/commands.py
bhvideoconverter/core/__init__.py
bhvideoconverter/core/exc.py
bhvideoconverter/core/version.py
bhvideoconverter/ext/__init__.py
bhvideoconverter/plugins/__init__.py
bhvideoconverter/templates/__init__.py
bhvideoconverter/templates/command1.jinja2
bhvideoconverter-1.1.dist-info/LICENSE.md
bhvideoconverter-1.1.dist-info/METADATA
bhvideoconverter-1.1.dist-info/WHEEL
bhvideoconverter-1.1.dist-info/entry_points.txt
bhvideoconverter-1.1.dist-info/top_level.txt
bhvideoconverter-1.1.dist-info/RECORD
