Metadata-Version: 2.1
Name: bhvideoconverter
Version: 1.1
Summary: convert any video format to any format :).!
Home-page: https://github.com/BandarHL/BHVideoConverter
Author: BandarHelal
Author-email: bandarhelal180@gmail.com
License: MIT
Platform: UNKNOWN
